goodmodslab_api/__init__.py
goodmodslab_api-0.4.dist-info/METADATA
goodmodslab_api-0.4.dist-info/WHEEL
goodmodslab_api-0.4.dist-info/RECORD
