Metadata-Version: 2.1
Name: goodmodslab-api
Version: 0.4
Summary: 
Author: KaBoT
Author-email: ac248384@gmail.com
Requires-Python: >=3.9,<4.0
Classifier: Programming Language :: Python :: 3
Classifier: Programming Language :: Python :: 3.9
Classifier: Programming Language :: Python :: 3.10
Classifier: Programming Language :: Python :: 3.11
Requires-Dist: fake-useragent (>=1.1.3,<2.0.0)
Requires-Dist: requests (>=2.29.0,<3.0.0)
